toilet/__init__.py
toilet/youngjae.py
toilet-0.0.0.9.dist-info/METADATA
toilet-0.0.0.9.dist-info/WHEEL
toilet-0.0.0.9.dist-info/top_level.txt
toilet-0.0.0.9.dist-info/RECORD
