Metadata-Version: 2.1
Name: toilet
Version: 0.0.0.9
Summary: toilet package
Home-page: https://blog.naver.com/dudwo567890
Author: hwangyoungjae
Author-email: dudwo56@gmail.com
License: MIT
Platform: UNKNOWN
Requires-Python: >=3
